console_scripts/__init__.py
console_scripts/app.py
console_scripts/config.py
console_scripts/consts.py
console_scripts/dc.py
console_scripts/dockerdev.py
console_scripts/gitup.py
console_scripts/setup_mtxlib.py
console_scripts/setup_nginx.py
console_scripts/setup_phpfpm.py
console_scripts/wordpress_helper.py
console_scripts/data/nginx.conf
demo/__init__.py
demo/admin.py
demo/apps.py
demo/models.py
demo/tests.py
demo/urls.py
demo/views.py
demo/data/1.txt
demo/migrations/0001_initial.py
demo/migrations/__init__.py
events/__init__.py
events/djcommand_handler.py
events/s3_event_handler.py
events/schedule_handler.py
events/zappa_commands.py
mitmaddons/__init__.py
mitmaddons/counter.py
mitmaddons/mt-http-redirect-requests.py
mitmaddons/options-simple.py
mitmaddons/lib/__init__.py
mitmaddons/lib/aaa.py
mtlibs/__init__.py
mtlibs/amplifyHelper.py
mtlibs/auth0_utils.py
mtlibs/cognito_util.py
mtlibs/config.py
mtlibs/container_config.py
mtlibs/docker_helper.py
mtlibs/frpcProc.py
mtlibs/fs.py
mtlibs/ghworker.py
mtlibs/github.py
mtlibs/json_encoder.py
mtlibs/jwt_helper.py
mtlibs/mtutils.py
mtlibs/oauthHelper.py
mtlibs/openvpnClientProc.py
mtlibs/openvpnProc.py
mtlibs/process_helper.py
mtlibs/tar_helper.py
mtlibs/testutils.py
mtlibs/tor_helper.py
mtlibs/aws/__init__.py
mtlibs/aws/ddb_helper.py
mtlibs/aws/s3_helper.py
mtlibs/aws/s3_imageresize.py
mtlibs/tests/__init__.py
mtlibs/tests/test_s3_helper.py
mtlibs/tool/__init__.py
mtlibs/tool/proxycheck.py
mtx_cloud/__init__.py
mtx_cloud/admin.py
mtx_cloud/apps.py
mtx_cloud/models.py
mtx_cloud/urls.py
mtx_cloud/views.py
mtx_cloud/management/__init__.py
mtx_cloud/management/commands/__init__.py
mtx_cloud/management/commands/mtx_collectstatic.py
mtx_cloud/management/commands/mtx_dump.py
mtx_cloud/management/commands/mtx_init_cloud.py
mtx_cloud/management/commands/mtx_storage.py
mtx_cloud/migrations/0001_initial.py
mtx_cloud/migrations/0002_initial.py
mtx_cloud/migrations/__init__.py
mtx_cloud/tests/__init__.py
mtx_sys/__init__.py
mtpylib-0.0.74.dist-info/METADATA
mtpylib-0.0.74.dist-info/WHEEL
mtpylib-0.0.74.dist-info/entry_points.txt
mtpylib-0.0.74.dist-info/top_level.txt
mtpylib-0.0.74.dist-info/RECORD
