Metadata-Version: 2.1
Name: mtpylib
Version: 0.0.74
Summary: The funniest joke in the world
Home-page: http://github.com/storborg/funniest
Author: Flying Circus
Author-email: flyingcircus@example.com
License: MIT
Keywords: funniest joke comedy flying circus
Platform: UNKNOWN
Classifier: Development Status :: 3 - Alpha
Classifier: License :: OSI Approved :: MIT License
Classifier: Programming Language :: Python :: 2.7
Classifier: Topic :: Text Processing :: Linguistic
Requires-Dist: markdown
Requires-Dist: flask
Requires-Dist: pyyaml
Requires-Dist: python-dotenv
Requires-Dist: requests (>=2.26.0)
Requires-Dist: lxml (>=4.2.3)
Requires-Dist: monotonic (>=1.5)
Requires-Dist: docker
Requires-Dist: wheel
Requires-Dist: boto3
Requires-Dist: aiohttp
Requires-Dist: django (>=4.0)
Requires-Dist: django-cors-headers
Requires-Dist: zappa
Requires-Dist: psycopg2-binary
Requires-Dist: django-s3-sqlite
Requires-Dist: django-s3-storage
Requires-Dist: django-storages
Requires-Dist: django-filter (>=2)
Requires-Dist: django-dotenv (==1.4.1)
Requires-Dist: django-extensions
Requires-Dist: djangorestframework
Requires-Dist: djangorestframework-simplejwt
Requires-Dist: pyjwt (>=2.0.0)
Requires-Dist: authlib
Requires-Dist: django-oauth-toolkit
Requires-Dist: django-lifecycle
Requires-Dist: pillow
Requires-Dist: packaging (>=21.0)
Requires-Dist: celery
